camcalib/__init__.py
camcalib/camcalib.py
CamCalib_jpvolt-0.1.0.dist-info/LICENSE
CamCalib_jpvolt-0.1.0.dist-info/METADATA
CamCalib_jpvolt-0.1.0.dist-info/WHEEL
CamCalib_jpvolt-0.1.0.dist-info/top_level.txt
CamCalib_jpvolt-0.1.0.dist-info/RECORD
