Metadata-Version: 2.1
Name: CamCalib-jpvolt
Version: 0.1.0
Summary: Opencv based camera calibration lib for stereo vision
Home-page: https://github.com/jpvolt/CameraCalibration
Author: João Pedro VOLTani
Author-email: jpvoltdeveloper@gmail.com
License: UNKNOWN
Platform: UNKNOWN
Classifier: Programming Language :: Python :: 3
Classifier: License :: OSI Approved :: MIT License
Classifier: Operating System :: OS Independent
